pyez_stats/__init__.py
pyez_stats/bayesian_statistics.py
pyez_stats/confidence_interval.py
pyez_stats/data.py
pyez_stats/distributions.py
pyez_stats/hypothesis_testing.py
pyez_stats/likelihoods.py
pyez_stats/pca.py
pyez_stats/regression.py
pyez_stats/statistic.py
pyez_stats-0.1.1.dist-info/METADATA
pyez_stats-0.1.1.dist-info/WHEEL
pyez_stats-0.1.1.dist-info/top_level.txt
pyez_stats-0.1.1.dist-info/RECORD
