Metadata-Version: 2.1
Name: pyez-stats
Version: 0.1.1
Summary: stats library
Home-page: https://pyez_stats.readthedocs.io/
Author: Jason DiBiase
Author-email: dibiasej3@gmail.com
License: MIT
Classifier: Intended Audience :: Developers
Classifier: License :: OSI Approved :: MIT License
Classifier: Programming Language :: Python
Classifier: Programming Language :: Python :: 3
Classifier: Programming Language :: Python :: 3.6
Classifier: Programming Language :: Python :: 3.7
Classifier: Programming Language :: Python :: 3.8
Classifier: Programming Language :: Python :: 3.9
Classifier: Programming Language :: Python :: 3.10
Classifier: Programming Language :: Python :: 3.11
Classifier: Operating System :: OS Independent
Requires-Dist: numpy
Requires-Dist: scipy
Requires-Dist: matplotlib
